adsctl/__about__.py
adsctl/__init__.py
adsctl/application.py
adsctl/client.py
adsctl/parse.py
adsctl/queries.py
adsctl/api/__init__.py
adsctl/api/utils.py
adsctl/api/asset/__init__.py
adsctl/api/asset/image.py
adsctl/api/campaign/__init__.py
adsctl/api/campaign/budget.py
adsctl/api/campaign/main.py
adsctl/api/campaign/status.py
adsctl/cli/__init__.py
adsctl/cli/auth.py
adsctl/cli/cli.py
adsctl/cli/config.py
adsctl/cli/utils.py
adsctl/cli/create/__init__.py
adsctl/cli/create/asset.py
adsctl/cli/create/main.py
adsctl/cli/edit/__init__.py
adsctl/cli/edit/campaign.py
adsctl/cli/edit/main.py
adsctl/cli/get/__init__.py
adsctl/cli/get/campaign.py
adsctl/cli/get/main.py
adsctl/config/__init__.py
adsctl/config/config_file.py
adsctl/config/model.py
adsctl/prompt/__init__.py
adsctl/prompt/cli.py
adsctl/prompt/completer.py
adsctl/prompt/key_bindings.py
adsctl/prompt/prompt.py
adsctl/utils/__init__.py
adsctl/utils/fs.py
adsctl-0.4.1.dist-info/METADATA
adsctl-0.4.1.dist-info/WHEEL
adsctl-0.4.1.dist-info/entry_points.txt
adsctl-0.4.1.dist-info/licenses/LICENSE.txt
adsctl-0.4.1.dist-info/RECORD
