Metadata-Version: 2.1
Name: adsctl
Version: 0.4.1
Summary: Google Ads Control CLI and Prompt
Project-URL: Documentation, https://github.com/danielfrg/adsctl#readme
Project-URL: Issues, https://github.com/danielfrg/adsctl/issues
Project-URL: Source, https://github.com/danielfrg/adsctl
Author-email: Daniel Rodriguez <daniel@danielfrg.com>
License-Expression: Apache-2.0
License-File: LICENSE.txt
Keywords: cli,google ads,google ads api,prompt
Classifier: Development Status :: 4 - Beta
Classifier: Programming Language :: Python
Classifier: Programming Language :: Python :: 3.8
Classifier: Programming Language :: Python :: 3.9
Classifier: Programming Language :: Python :: 3.10
Classifier: Programming Language :: Python :: 3.11
Classifier: Programming Language :: Python :: Implementation :: CPython
Classifier: Programming Language :: Python :: Implementation :: PyPy
Requires-Python: >=3.8
Requires-Dist: click>=8.1
Requires-Dist: google-ads>=20.0.0
Requires-Dist: jinja2>=3.1.0
Requires-Dist: pandas>=2.0.0
Requires-Dist: pillow>=9.5.0
Requires-Dist: prompt-toolkit>=3.0.38
Requires-Dist: pydantic<2.0.0,>=1.10.0
Requires-Dist: tabulate>=0.9.0
Requires-Dist: tomli-w>=1.0
Requires-Dist: tomlkit>=0.11.1
Provides-Extra: test
Requires-Dist: coverage[toml]; extra == 'test'
Requires-Dist: pytest; extra == 'test'
Requires-Dist: pytest-cov; extra == 'test'
